[{"id":1001,"nombre":"Alberto Cardenas","correo":"albertoCar@hotmail","telefono":41320402,"tipoUsuario":"coordinador"},{"id":1002,"nombre":"Gloria Borger","correo":"globorger@hotmail","telefono":10001012,"tipoUsuario":"aspirante"},{"id":99999,"nombre":"lola","correo":"lola@lelo.com","telefono":34234234,"tipoUsuario":"aspirante","cursos":[{"idCurso":1001,"nombre":"Curso b치sico node","descripcion":"Curso b치sico node","valor":300000,"estado":"disponible"},{"idCurso":1004,"nombre":"MATLAB","descripcion":"MATLAB PARA DUMMIES","valor":2000000,"estado":"disponible"},{"idCurso":912912,"nombre":"Filosofia aplicada","descripcion":"Descripci칩n filos칩fica","valor":201000,"modalidad":"ninguna","intensidad":"todo es relativo","estado":"disponible"}]}]